[
	{"drawDate": "04-01-2024", "one" : "11*21", "two" : "", "three" : "25*18"},
	{"drawDate": "04-02-2024", "one" : "09*39", "two" : "", "three" : "29*03"},
	{"drawDate": "04-03-2024", "one" : "16*35", "two" : "", "three" : "27*37"},
	{"drawDate": "04-04-2024", "one" : "25*17", "two" : "", "three" : "05*29"},
	{"drawDate": "04-05-2024", "one" : "03*37", "two" : "", "three" : "31*34"},
	{"drawDate": "04-06-2024", "one" : "23*01", "two" : "", "three" : "34*17"},
	{"drawDate": "04-07-2024", "one" : "02*21", "two" : "", "three" : "02*08"},
	{"drawDate": "04-08-2024", "one" : "21*18", "two" : "", "three" : "04*29"},
	{"drawDate": "04-09-2024", "one" : "21*09", "two" : "", "three" : "22*38"},
	{"drawDate": "04-10-2024", "one" : "32*06", "two" : "", "three" : "18*32"},
	{"drawDate": "04-11-2024", "one" : "12*O2", "two" : "", "three" : "12*03"},
	{"drawDate": "04-12-2024", "one" : "36*32", "two" : "", "three" : "17*19"},
	{"drawDate": "04-13-2024", "one" : "12*08", "two" : "", "three" : "16*04"},
	{"drawDate": "04-14-2024", "one" : "12*12", "two" : "", "three" : "27*28"},
	{"drawDate": "04-15-2024", "one" : "18*39", "two" : "", "three" : "16*03"},
	{"drawDate": "04-16-2024", "one" : "13*29", "two" : "", "three" : "01*18"},
	{"drawDate": "04-17-2024", "one" : "07*32", "two" : "", "three" : "30*39"},
	{"drawDate": "04-18-2024", "one" : "31*18", "two" : "", "three" : "38*26"},
	{"drawDate": "04-19-2024", "one" : "13*22", "two" : "", "three" : "10*06"},
	{"drawDate": "04-20-2024", "one" : "02*16", "two" : "", "three" : "12*04"},
	{"drawDate": "04-21-2024", "one" : "04*21", "two" : "", "three" : "16*03"},
	{"drawDate": "04-22-2024", "one" : "14*22", "two" : "", "three" : "06*21"},
	{"drawDate": "04-23-2024", "one" : "06*36", "two" : "", "three" : "12*11"},
	{"drawDate": "04-24-2024", "one" : "32*20", "two" : "", "three" : "17*09"},
	{"drawDate": "04-25-2024", "one" : "27*18", "two" : "", "three" : "38*35"},
	{"drawDate": "04-26-2024", "one" : "27*25", "two" : "", "three" : "24*07"},
	{"drawDate": "04-27-2024", "one" : "36*35", "two" : "", "three" : "06*31"},
	{"drawDate": "04-28-2024", "one" : "26*22", "two" : "", "three" : "08*39"},
	{"drawDate": "04-29-2024", "one" : "35*12", "two" : "", "three" : "16*09"},
	{"drawDate": "04-30-2024", "one" : "40*37", "two" : "", "three" : "20*29"}
]